banner_of_light_research_assistant/__about__.py
banner_of_light_research_assistant/__init__.py
banner_of_light_research_assistant/cli.py
banner_of_light_research_assistant/pdf_utils.py
banner_of_light_research_assistant/read_pdf.py
banner_of_light_research_assistant-0.0.2.dist-info/METADATA
banner_of_light_research_assistant-0.0.2.dist-info/WHEEL
banner_of_light_research_assistant-0.0.2.dist-info/entry_points.txt
banner_of_light_research_assistant-0.0.2.dist-info/licenses/LICENSE.txt
banner_of_light_research_assistant-0.0.2.dist-info/RECORD
