Metadata-Version: 2.3
Name: banner-of-light-research-assistant
Version: 0.0.2
Summary: This application prepares data from the 19th century newspaper Banner of Light to be analyzed by a AI research assistant powered by OpenAI
Project-URL: Documentation, https://github.com/unknown/banner-of-light-research-assistant#readme
Project-URL: Issues, https://github.com/unknown/banner-of-light-research-assistant/issues
Project-URL: Source, https://github.com/unknown/banner-of-light-research-assistant
Author-email: Theodore Cowan <t@theodore.me>
License-Expression: MIT
License-File: LICENSE.txt
Classifier: Development Status :: 4 - Beta
Classifier: Programming Language :: Python
Classifier: Programming Language :: Python :: 3.11
Classifier: Programming Language :: Python :: 3.12
Classifier: Programming Language :: Python :: Implementation :: CPython
Classifier: Programming Language :: Python :: Implementation :: PyPy
Requires-Python: >=3.11
Requires-Dist: opencv-python
Requires-Dist: pdfplumber
Requires-Dist: pypdf2
